scache/__init__.py
scache/lib.py
ran_cache-0.1.0.dist-info/LICENSE
ran_cache-0.1.0.dist-info/METADATA
ran_cache-0.1.0.dist-info/WHEEL
ran_cache-0.1.0.dist-info/top_level.txt
ran_cache-0.1.0.dist-info/RECORD
