Metadata-Version: 2.1
Name: ran-cache
Version: 0.1.0
Summary: A class for caching in a session.
Home-page: https://github.com/01-ERFA/session-cache-package
Author: Ran
Author-email: star01-fym@gmail.com
License: MIT
Classifier: Programming Language :: Python :: 3
Classifier: License :: OSI Approved :: MIT License
Classifier: Operating System :: OS Independent
License-File: LICENSE
